llama_index/graph_stores/neo4j/__init__.py
llama_index/graph_stores/neo4j/base.py
flying_delta_graph_stores_neo4j-0.1.0.dist-info/METADATA
flying_delta_graph_stores_neo4j-0.1.0.dist-info/WHEEL
flying_delta_graph_stores_neo4j-0.1.0.dist-info/RECORD
